MEFrpLib/__init__.py
MEFrpLib/auth.py
MEFrpLib/models.py
MEFrpLib/public.py
MEFrpLib-2.2.7.dist-info/LICENSE
MEFrpLib-2.2.7.dist-info/METADATA
MEFrpLib-2.2.7.dist-info/WHEEL
MEFrpLib-2.2.7.dist-info/top_level.txt
MEFrpLib-2.2.7.dist-info/RECORD
