Metadata-Version: 2.1
Name: MEFrpLib
Version: 2.2.7
Summary: UNKNOWN
Home-page: https://github.com/LxHTT/MEFrpLib
Author: LxHTT
Author-email: lxhtt@vip.qq.com
License: MIT
Project-URL: Documentation, https://github.com/LxHTT/MEFrpLib/blob/master/README.md
Project-URL: Source Code, https://github.com/LxHTT/MEFrpLib
Project-URL: Bug Tracker, https://github.com/LxHTT/MEFrpLib/issues
Platform: UNKNOWN
Classifier: Programming Language :: Python :: 3.8
Classifier: License :: OSI Approved :: MIT License
Classifier: Operating System :: OS Independent
Requires-Python: >=3.7
Requires-Dist: requests >=2.31.0
